countrynames/__init__.py
countrynames/compile.py
countrynames/data.py
countrynames/data.yaml
countrynames/mappings.py
countrynames/py.typed
countrynames/util.py
countrynames-1.16.7.dist-info/METADATA
countrynames-1.16.7.dist-info/WHEEL
countrynames-1.16.7.dist-info/licenses/LICENSE
countrynames-1.16.7.dist-info/RECORD
