Metadata-Version: 2.4
Name: countrynames
Version: 1.16.7
Summary: A library to map country names to 2-letter ISO codes.
Project-URL: Documentation, https://github.com/opensanctions/countrynames/
Project-URL: Repository, https://github.com/opensanctions/countrynames.git
Project-URL: Issues, https://github.com/opensanctions/countrynames/issues
Author-email: OpenSanctions <info@opensanctions.org>
License: The MIT License (MIT)
License-File: LICENSE
Classifier: Intended Audience :: Developers
Classifier: License :: OSI Approved :: MIT License
Classifier: Operating System :: OS Independent
Classifier: Programming Language :: Python :: 3.11
Classifier: Programming Language :: Python :: 3.12
Requires-Python: >=3.10
Requires-Dist: banal<1.1.0,>=1.0.6
Requires-Dist: normality>=2.5.0
Requires-Dist: pyyaml<7.0.0,>=5.0.0
Requires-Dist: rapidfuzz<4.0.0,>=3.9.0
Provides-Extra: dev
Requires-Dist: build; extra == 'dev'
Requires-Dist: bump2version; extra == 'dev'
Requires-Dist: coverage>=4.1; extra == 'dev'
Requires-Dist: mypy; extra == 'dev'
Requires-Dist: pytest; extra == 'dev'
Requires-Dist: pytest-cov; extra == 'dev'
Requires-Dist: ruff; extra == 'dev'
Requires-Dist: types-pyyaml; extra == 'dev'
